[
    {
        "title": "Folding table lamp eye protection touch dimmable LED lamp student dormitory bedroom reading USB rechargeable table lamp ",
        "link": "//www.aliexpress.us/item/3256805138057751.html?algo_pvid=9a78d455-aab0-4272-8fc5-d40db428b4c0&algo_exp_id=9a78d455-aab0-4272-8fc5-d40db428b4c0-0&pdp_npi=4%40dis%21USD%2114.53%210.99%21%21%21103.90%21%21%402101d4a717022697252071229e993f%2112000032629180287%21sea%21US%210%21AB&curPageLogUid=dF2GHtJDA0Ug",
        "price": 0.99,
        "keyword": "desk lamp",
        "priority": "high"
    },
    {
        "title": "50 Sheets Creative Transparent PET Waterproof Posted It Sticky Note Pads Notepads Posits for School Stationery Office Supplies ",
        "link": "//www.aliexpress.us/item/3256805070162639.html?algo_pvid=cc29e2ce-044f-4f13-a7dc-bd832fbf7800&algo_exp_id=cc29e2ce-044f-4f13-a7dc-bd832fbf7800-0&pdp_npi=4%40dis%21USD%211.56%210.87%21%21%2111.19%21%21%402101d4a717022697210331188e993f%2112000032382260125%21sea%21US%210%21AB&curPageLogUid=JN5KNQJhLSJf",
        "price": 0.87,
        "keyword": "sticky notes",
        "priority": "med"
    }
]